<core:FragmentDefinition xmlns="sap.m"
	xmlns:core="sap.ui.core">
	<Dialog id="createModifyLine" title="{i18n>modifyLine}">

		<content>
			<HBox alignItems="Center" class="dialogForm">
				<Label text="{i18n>name}" width="6rem"></Label>
				<Input />
			</HBox>

			<HBox alignItems="Center" class="dialogForm">
				<Label text="{i18n>description}" width="6rem"></Label>
				<Input />
			</HBox>
		</content>

		<buttons>
			<Button icon="sap-icon://create" />
			<Button icon="sap-icon://save" />
			<Button text="{i18n>cancel}" press="onCancel" />

		</buttons>
	</Dialog>
</core:FragmentDefinition>