{
	"linkTypeToDisplay":"",
	"elementList": [
					{
						"type": "SO1",
						"acpId": "10003242224",
						"reference": "10003242224",
						"reviewEnd": "28/11/2016",
						"note": "note",
						"familyTarget": "FAL-PYLON RH",
						"confirmedTime": "83",
						"stv": "",
						"acpWorkstation": "",
						"ca": "WA999",
						"fatherLink": "",
						"blockingReason": "NDC",
						"userStatus": "OW00 SFBL SFFI",
						"executionStation": "",
						"originWorkstation": "V1040A-J",
						"tdl": "W2.1",
						"upperFamily": "",
						"zoning": "P8",
						"materialDescription": "INST-FWD PWRF",
						"ata": "5720",
						"father_Type": "",
						"predId": ""
					},
					{
						"type": "NC",
						"acpId": "6789685",
						"reference": "6789685",
						"reviewEnd": "",
						"note": "note",
						"familyTarget": "",
						"confirmedTime": "",
						"stv": "",
						"acpWorkstation": "",
						"ca": "",
						"fatherLink": "",
						"blockingReason": "",
						"userStatus": "",
						"executionStation": "",
						"originWorkstation": "",
						"tdl": "",
						"upperFamily": "",
						"zoning": "",
						"materialDescription": "Broken bracket",
						"ata": "",
						"father_Type": "SO1",
						"predId": "10003242224",
						"linkType": "X"
					},
					{
						"type": "SO3",
						"acpId": "10003678688",
						"reference": "10003678688",
						"reviewEnd": "28/11/2016",
						"note": "note",
						"familyTarget": "FAL-caRGO",
						"confirmedTime": "54",
						"stv": "",
						"acpWorkstation": "",
						"ca": "WA999",
						"fatherLink": "",
						"blockingReason": "SHOR",
						"userStatus": "OW00 SFFI",
						"executionStation": "",
						"originWorkstation": "V1040A-J",
						"tdl": "W2.1",
						"upperFamily": "",
						"zoning": "P8",
						"materialDescription": "INST-CLS",
						"ata": "5720",
						"father_Type": "NC",
						"predId": "6789685",
						"linkType": "X"
					},
					{
						"type": "NC",
						"acpId": "1000367868800",
						"reference": "1000367868800",
						"reviewEnd": "28/11/2016",
						"note": "note",
						"familyTarget": "FAL-caRGO",
						"confirmedTime": "54",
						"stv": "",
						"acpWorkstation": "",
						"ca": "WA999",
						"fatherLink": "",
						"blockingReason": "SHOR",
						"userStatus": "OW00 SFFI",
						"executionStation": "",
						"originWorkstation": "V1040A-J",
						"tdl": "W2.1",
						"upperFamily": "",
						"zoning": "P8",
						"materialDescription": "INST-CLS",
						"ata": "5720",
						"fatherType": "SO1",
						"predId": "10003678688",
						"linkType": ""
					},
					{
						"type": "SO1",
						"acpId": "10003242225",
						"reference": "10003242225",
						"reviewEnd": "28/11/2016",
						"note": "note",
						"familyTarget": "FAL-PYLON RH",
						"confirmedTime": "83",
						"stv": "",
						"acpWorkstation": "",
						"ca": "WA999",
						"fatherLink": "",
						"blockingReason": "NDC",
						"userStatus": "OW00 SFBL SFFI",
						"executionStation": "",
						"originWorkstation": "V1040A-J",
						"tdl": "W2.1",
						"upperFamily": "",
						"zoning": "P8",
						"materialDescription": "INST-FWD PWRF",
						"ata": "5720",
						"fatherType": "",
						"predId": "",
						"linkType": "X"
					},
					{
						"type": "NC",
						"acpId": "6789686",
						"reference": "6789686",
						"reviewEnd": "",
						"note": "note",
						"familyTarget": "",
						"confirmedTime": "",
						"stv": "",
						"acpWorkstation": "",
						"ca": "",
						"fatherLink": "",
						"blockingReason": "",
						"userStatus": "",
						"executionStation": "",
						"originWorkstation": "",
						"tdl": "",
						"upperFamily": "",
						"zoning": "",
						"materialDescription": "Broken bracket",
						"ata": "",
						"fatherType": "SO1",
						"predId": "10003242225",
						"linkType": ""
					},
					{
						"type": "SO3",
						"acpId": "10003678689",
						"reference": "10003678689",
						"reviewEnd": "28/11/2016",
						"note": "note",
						"familyTarget": "FAL-caRGO",
						"confirmedTime": "54",
						"stv": "",
						"acpWorkstation": "",
						"ca": "WA999",
						"fatherLink": "",
						"blockingReason": "SHOR",
						"userStatus": "OW00 SFFI",
						"executionStation": "",
						"originWorkstation": "V1040A-J",
						"tdl": "W2.1",
						"upperFamily": "",
						"zoning": "P8",
						"materialDescription": "INST-CLS",
						"ata": "5720",
						"fatherType": "NC",
						"predId": "6789686",
						"linkType": ""
					},
					{
						"type": "NC",
						"acpId": "10003678689",
						"reference": "10003678689",
						"reviewEnd": "28/11/2016",
						"note": "note",
						"familyTarget": "FAL-caRGO",
						"confirmedTime": "54",
						"stv": "",
						"acpWorkstation": "",
						"ca": "WA999",
						"fatherLink": "",
						"blockingReason": "SHOR",
						"userStatus": "OW00 SFFI",
						"executionStation": "",
						"originWorkstation": "V1040A-J",
						"tdl": "W2.1",
						"upperFamily": "",
						"zoning": "P8",
						"materialDescription": "INST-CLS",
						"ata": "5720",
						"fatherType": "SO1",
						"predId": "10003242225",
						"linkType": ""
					},
					{
						"type": "SO1",
						"acpId": "10003242227",
						"reference": "10003242227",
						"reviewEnd": "28/11/2016",
						"note": "note",
						"familyTarget": "FAL-PYLON RH",
						"confirmedTime": "83",
						"stv": "",
						"acpWorkstation": "",
						"ca": "WA999",
						"fatherLink": "",
						"blockingReason": "NDC",
						"userStatus": "OW00 SFBL SFFI",
						"executionStation": "",
						"originWorkstation": "V1040A-J",
						"tdl": "W2.1",
						"upperFamily": "",
						"zoning": "P8",
						"materialDescription": "INST-FWD PWRF",
						"ata": "5720",
						"fatherType": "",
						"predId": "",
						"linkType": ""
					},
					{
						"type": "NC",
						"acpId": "6789687",
						"reference": "6789687",
						"reviewEnd": "",
						"note": "note",
						"familyTarget": "",
						"confirmedTime": "",
						"stv": "",
						"acpWorkstation": "",
						"ca": "",
						"fatherLink": "",
						"blockingReason": "",
						"userStatus": "",
						"executionStation": "",
						"originWorkstation": "",
						"tdl": "",
						"upperFamily": "",
						"zoning": "",
						"materialDescription": "Broken bracket",
						"ata": "",
						"fatherType": "SO1",
						"predId": "10003242227",
						"linkType": ""
					},
					{
						"type": "SO3",
						"acpId": "10003678690",
						"reference": "10003678690",
						"reviewEnd": "28/11/2016",
						"note": "note",
						"familyTarget": "FAL-caRGO",
						"confirmedTime": "54",
						"stv": "",
						"acpWorkstation": "",
						"ca": "WA999",
						"fatherLink": "",
						"blockingReason": "SHOR",
						"userStatus": "OW00 SFFI",
						"executionStation": "",
						"originWorkstation": "V1040A-J",
						"tdl": "W2.1",
						"upperFamily": "",
						"zoning": "P8",
						"materialDescription": "INST-CLS",
						"ata": "5720",
						"fatherType": "NC",
						"predId": "6789687",
						"linkType": ""
					},
					{
						"type": "NC",
						"acpId": "10003678690",
						"reference": "10003678690",
						"reviewEnd": "28/11/2016",
						"note": "note",
						"familyTarget": "FAL-caRGO",
						"confirmedTime": "54",
						"stv": "",
						"acpWorkstation": "",
						"ca": "WA999",
						"fatherLink": "",
						"blockingReason": "SHOR",
						"userStatus": "OW00 SFFI",
						"executionStation": "",
						"originWorkstation": "V1040A-J",
						"tdl": "W2.1",
						"upperFamily": "",
						"zoning": "P8",
						"materialDescription": "INST-CLS",
						"ata": "5720",
						"fatherType": "SO1",
						"predId": "10003242227",
						"linkType": ""
					},
					{
						"type": "NC",
						"acpId": "10007358411",
						"reference": "10007358411",
						"reviewEnd": "28/11/2016",
						"note": "note",
						"familyTarget": "FAL-caRGO",
						"confirmedTime": "54",
						"stv": "",
						"acpWorkstation": "",
						"ca": "WA999",
						"fatherLink": "",
						"blockingReason": "SHOR",
						"userStatus": "OW00 SFFI",
						"executionStation": "",
						"originWorkstation": "V1040A-J",
						"tdl": "W2.1",
						"upperFamily": "",
						"zoning": "P8",
						"materialDescription": "INST-CLS",
						"ata": "5720",
						"fatherType": "SO1",
						"predId": "?",
						"linkType": ""
					}
				]
}				